frames_depot/__init__.py
frames_depot/frames_depot.py
frames_depot/main.py
gh_frames_depot-1.0.0.dist-info/METADATA
gh_frames_depot-1.0.0.dist-info/WHEEL
gh_frames_depot-1.0.0.dist-info/top_level.txt
gh_frames_depot-1.0.0.dist-info/RECORD
