Metadata-Version: 2.1
Name: gh-frames-depot
Version: 1.0.0
Summary: Package for buffering frames in memory and sharing them between processes.
Home-page: https://github.com/m-ghiani/FRAMES_DEPOT
Author: Massimo Ghiani
Author-email: m.ghiani@gmail.com
License: MIT
Classifier: Development Status :: 5 - Production/Stable
Classifier: Intended Audience :: Developers
Classifier: License :: OSI Approved :: MIT License
Classifier: Programming Language :: Python :: 3
Classifier: Programming Language :: Python :: 3.6
Classifier: Programming Language :: Python :: 3.7
Classifier: Programming Language :: Python :: 3.8
Classifier: Programming Language :: Python :: 3.9
Classifier: Programming Language :: Python :: 3.10
Classifier: Programming Language :: Python :: 3.11
Classifier: Programming Language :: Python :: 3.12
Requires-Python: >=3.10
Requires-Dist: numpy >=1.26.2
Requires-Dist: asyncio >=3.4.3
